odoo/addons/stock_restrict_lot_update/README.rst
odoo/addons/stock_restrict_lot_update/__init__.py
odoo/addons/stock_restrict_lot_update/__manifest__.py
odoo/addons/stock_restrict_lot_update/i18n/it.po
odoo/addons/stock_restrict_lot_update/i18n/stock_restrict_lot_update.pot
odoo/addons/stock_restrict_lot_update/models/__init__.py
odoo/addons/stock_restrict_lot_update/models/res_company.py
odoo/addons/stock_restrict_lot_update/models/res_config_settings.py
odoo/addons/stock_restrict_lot_update/models/stock_move.py
odoo/addons/stock_restrict_lot_update/readme/CONTEXT.rst
odoo/addons/stock_restrict_lot_update/readme/CONTRIBUTORS.rst
odoo/addons/stock_restrict_lot_update/readme/DESCRIPTION.rst
odoo/addons/stock_restrict_lot_update/readme/USAGE.rst
odoo/addons/stock_restrict_lot_update/static/description/icon.png
odoo/addons/stock_restrict_lot_update/static/description/index.html
odoo/addons/stock_restrict_lot_update/tests/__init__.py
odoo/addons/stock_restrict_lot_update/tests/test_restrict_lot_update.py
odoo/addons/stock_restrict_lot_update/views/res_config_settings_views.xml
odoo/addons/stock_restrict_lot_update/views/stock_picking_views.xml
odoo14_addon_stock_restrict_lot_update-14.0.1.0.1.dev3.dist-info/METADATA
odoo14_addon_stock_restrict_lot_update-14.0.1.0.1.dev3.dist-info/WHEEL
odoo14_addon_stock_restrict_lot_update-14.0.1.0.1.dev3.dist-info/top_level.txt
odoo14_addon_stock_restrict_lot_update-14.0.1.0.1.dev3.dist-info/RECORD
